keystore_mcp/__init__.py
keystore_mcp/__main__.py
keystore_mcp/server.py
keystore_mcp/crypto/__init__.py
keystore_mcp/crypto/cipher.py
keystore_mcp/crypto/kdf.py
keystore_mcp/crypto/mac.py
keystore_mcp/prompts/__init__.py
keystore_mcp/prompts/backup.py
keystore_mcp/prompts/migration.py
keystore_mcp/prompts/recovery.py
keystore_mcp/resources/__init__.py
keystore_mcp/resources/examples.py
keystore_mcp/resources/security.py
keystore_mcp/resources/specification.py
keystore_mcp/tools/__init__.py
keystore_mcp/tools/batch.py
keystore_mcp/tools/decrypt.py
keystore_mcp/tools/encrypt.py
keystore_mcp/tools/file_ops.py
keystore_mcp/tools/validation.py
keystore_mcp/utils/__init__.py
keystore_mcp/utils/file_utils.py
keystore_mcp/utils/validation.py
keystore_mcp_server-1.0.0.dist-info/METADATA
keystore_mcp_server-1.0.0.dist-info/WHEEL
keystore_mcp_server-1.0.0.dist-info/entry_points.txt
keystore_mcp_server-1.0.0.dist-info/RECORD
