Metadata-Version: 2.4
Name: keystore-mcp-server
Version: 1.0.0
Summary: MCP server for Ethereum keystore encryption, decryption, and management
Project-URL: Homepage, https://github.com/nirholas/ethereum-wallet-toolkit
Project-URL: Repository, https://github.com/nirholas/ethereum-wallet-toolkit/tree/main/keystore-mcp-server
Project-URL: Documentation, https://github.com/nirholas/ethereum-wallet-toolkit/blob/main/keystore-mcp-server/README.md
Author-email: nirholas <nich@ethereum.tools>
License-Expression: MIT
Keywords: cryptocurrency,encryption,ethereum,keystore,mcp,web3
Classifier: Development Status :: 4 - Beta
Classifier: Intended Audience :: Developers
Classifier: License :: OSI Approved :: MIT License
Classifier: Programming Language :: Python :: 3
Classifier: Programming Language :: Python :: 3.11
Classifier: Programming Language :: Python :: 3.12
Classifier: Topic :: Security :: Cryptography
Requires-Python: >=3.11
Requires-Dist: cryptography>=41.0.0
Requires-Dist: eth-account>=0.10.0
Requires-Dist: eth-keyfile>=0.8.0
Requires-Dist: eth-keys>=0.5.0
Requires-Dist: eth-utils>=2.3.0
Requires-Dist: mcp>=1.0.0
Requires-Dist: pydantic>=2.0.0
Provides-Extra: dev
Requires-Dist: black>=23.0.0; extra == 'dev'
Requires-Dist: isort>=5.12.0; extra == 'dev'
Requires-Dist: mypy>=1.5.0; extra == 'dev'
Requires-Dist: pytest-asyncio>=0.21.0; extra == 'dev'
Requires-Dist: pytest-cov>=4.1.0; extra == 'dev'
Requires-Dist: pytest>=7.4.0; extra == 'dev'
